CODE_OF_CONDUCT.md
MANIFEST.in
README.md
setup.py
docs/gen_ref_pages.py
qtcodes/VERSION.txt
qtcodes/__init__.py
qtcodes.egg-info/PKG-INFO
qtcodes.egg-info/SOURCES.txt
qtcodes.egg-info/dependency_links.txt
qtcodes.egg-info/requires.txt
qtcodes.egg-info/top_level.txt
qtcodes/circuits/__init__.py
qtcodes/circuits/base.py
qtcodes/circuits/circ.py
qtcodes/circuits/qubit_types.py
qtcodes/circuits/repetition.py
qtcodes/circuits/rotated_surface.py
qtcodes/circuits/xxzz.py
qtcodes/circuits/xzzx.py
qtcodes/common/__init__.py
qtcodes/common/constants.py
qtcodes/fitters/__init__.py
qtcodes/fitters/base.py
qtcodes/fitters/lattice_decoder.py
qtcodes/fitters/repetition.py
qtcodes/fitters/rotated_surface.py
qtcodes/tools/__init__.py
qtcodes/tools/benchmarking.py