Metadata-Version: 2.1
Name: qtcodes
Version: 0.2.0
Summary: Qiskit Topological Codes
Home-page: https://github.com/yaleqc/qtcodes
Author: Shantanu Jha
Author-email: shantanu.rajesh.jha@gmail.com
License: Apache 2.0
Project-URL: Bug Tracker, https://github.com/yaleqc/qtcodes/issues
Project-URL: Documentation, https://yaleqc.com/qtcodes/
Project-URL: Source Code, https://github.com/yaleqc/qtcodes
Project-URL: Tutorials, https://github.com/yaleqc/qtcodes/tree/master/tutorials
Project-URL: Tests, https://github.com/yaleqc/qtcodes/tree/master/tests
Keywords: qiskit topological surface codes qec quantum error correction
Platform: UNKNOWN
Classifier: Environment :: Console
Classifier: License :: OSI Approved :: Apache Software License
Classifier: Intended Audience :: Developers
Classifier: Intended Audience :: Science/Research
Classifier: Operating System :: Microsoft :: Windows
Classifier: Operating System :: MacOS :: MacOS X
Classifier: Operating System :: POSIX :: Linux
Classifier: Programming Language :: Python :: 3 :: Only
Classifier: Programming Language :: Python :: 3.6
Classifier: Programming Language :: Python :: 3.7
Classifier: Programming Language :: Python :: 3.8
Classifier: Topic :: Scientific/Engineering
Requires-Python: >=3.6
Provides-Extra: dev
